snakemake_interface_scheduler_plugins/__init__.py
snakemake_interface_scheduler_plugins/base.py
snakemake_interface_scheduler_plugins/common.py
snakemake_interface_scheduler_plugins/settings.py
snakemake_interface_scheduler_plugins/tests.py
snakemake_interface_scheduler_plugins/interfaces/__init__.py
snakemake_interface_scheduler_plugins/interfaces/dag.py
snakemake_interface_scheduler_plugins/interfaces/jobs.py
snakemake_interface_scheduler_plugins/registry/__init__.py
snakemake_interface_scheduler_plugins/registry/plugin.py
snakemake_interface_scheduler_plugins-2.0.1.dist-info/METADATA
snakemake_interface_scheduler_plugins-2.0.1.dist-info/WHEEL
snakemake_interface_scheduler_plugins-2.0.1.dist-info/licenses/LICENSE
snakemake_interface_scheduler_plugins-2.0.1.dist-info/RECORD
