Metadata-Version: 2.4
Name: snakemake-interface-scheduler-plugins
Version: 2.0.1
Summary: Scheduler plugin interface for snakemake
Author-email: Johannes Köster <johannes.koester@uni-due.de>
License-File: LICENSE
Requires-Python: <4.0,>=3.11
Requires-Dist: snakemake-interface-common<2.0,>=1.20.1
